outlier_removal_101703121/outlier_101703121.py
outlier_removal_101703121-0.1.dist-info/METADATA
outlier_removal_101703121-0.1.dist-info/WHEEL
outlier_removal_101703121-0.1.dist-info/top_level.txt
outlier_removal_101703121-0.1.dist-info/RECORD
