Metadata-Version: 2.1
Name: outlier-removal-101703121
Version: 0.1
Summary: Remove Outliers from the dataset
Home-page: UNKNOWN
Author: Atishay jain
Author-email: atishay21@gmail.com
License: MIT
Platform: UNKNOWN
Classifier: Development Status :: 3 - Alpha
Classifier: Intended Audience :: Developers
Classifier: Topic :: Software Development :: Build Tools
Classifier: License :: OSI Approved :: MIT License
Classifier: Programming Language :: Python :: 3.7
Requires-Dist: pandas
Requires-Dist: numpy
